purpose_classifier/__init__.py
purpose_classifier/bert_adapter.py
purpose_classifier/bert_classifier.py
purpose_classifier/classifier.py
purpose_classifier/domain_context_analyzer.py
purpose_classifier/lightgbm_classifier.py
purpose_classifier/optimized_embeddings.py
purpose_classifier/semantic_pattern_matcher.py
purpose_classifier/config/__init__.py
purpose_classifier/config/config.py
purpose_classifier/config/path_helper.py
purpose_classifier/config/settings.py
purpose_classifier/data/__init__.py
purpose_classifier/data/category_purpose_codes.json
purpose_classifier/data/iso20022_purpose_codes.json
purpose_classifier/data/purpose_codes.json
purpose_classifier/data/sample_messages.json
purpose_classifier/domain_enhancers/__init__.py
purpose_classifier/domain_enhancers/adaptive_confidence.py
purpose_classifier/domain_enhancers/base_enhancer.py
purpose_classifier/domain_enhancers/card_payment_enhancer_semantic.py
purpose_classifier/domain_enhancers/category_purpose_enhancer_semantic.py
purpose_classifier/domain_enhancers/charitable_donation_enhancer_semantic.py
purpose_classifier/domain_enhancers/collaborative_enhancer.py
purpose_classifier/domain_enhancers/context_aware_enhancer_semantic.py
purpose_classifier/domain_enhancers/court_payment_enhancer_semantic.py
purpose_classifier/domain_enhancers/cover_payment_enhancer_semantic.py
purpose_classifier/domain_enhancers/cross_border_enhancer_semantic.py
purpose_classifier/domain_enhancers/dividend_enhancer.py
purpose_classifier/domain_enhancers/education_enhancer_semantic.py
purpose_classifier/domain_enhancers/enhanced_manager.py
purpose_classifier/domain_enhancers/enhancer_manager.py
purpose_classifier/domain_enhancers/financial_services_enhancer_semantic.py
purpose_classifier/domain_enhancers/forex_enhancer_semantic.py
purpose_classifier/domain_enhancers/goods_enhancer_semantic.py
purpose_classifier/domain_enhancers/government_payment_enhancer_semantic.py
purpose_classifier-1.4.0.dist-info/licenses/LICENSE
purpose_classifier-1.4.0.dist-info/METADATA
purpose_classifier-1.4.0.dist-info/WHEEL
purpose_classifier-1.4.0.dist-info/entry_points.txt
purpose_classifier-1.4.0.dist-info/top_level.txt
purpose_classifier-1.4.0.dist-info/RECORD
