Metadata-Version: 2.4
Name: purpose-classifier
Version: 1.4.0
Summary: A high-accuracy machine learning system for classifying purpose codes and category purpose codes from SWIFT message narrations
Home-page: https://github.com/solchos/purpose-classifier-package
Author: Solchos
Author-email: solchos@gmail.com
Classifier: Programming Language :: Python :: 3
Classifier: License :: OSI Approved :: MIT License
Classifier: Operating System :: OS Independent
Classifier: Development Status :: 5 - Production/Stable
Classifier: Intended Audience :: Financial and Insurance Industry
Classifier: Topic :: Office/Business :: Financial
Classifier: Topic :: Scientific/Engineering :: Artificial Intelligence
Requires-Python: >=3.8
License-File: LICENSE
Requires-Dist: scikit-learn>=1.0.2
Requires-Dist: pandas>=1.4.2
Requires-Dist: numpy>=1.22.3
Requires-Dist: nltk>=3.7
Requires-Dist: joblib>=1.1.0
Requires-Dist: matplotlib>=3.5.2
Requires-Dist: tqdm>=4.64.0
Requires-Dist: regex>=2022.4.24
Requires-Dist: lightgbm>=3.3.2
Requires-Dist: tabulate>=0.8.9
Requires-Dist: torch>=1.10.0
Requires-Dist: transformers>=4.18.0
Dynamic: author
Dynamic: author-email
Dynamic: classifier
Dynamic: description
Dynamic: description-content-type
Dynamic: home-page
Dynamic: license-file
Dynamic: requires-dist
Dynamic: requires-python
Dynamic: summary
